easy_ml_config/__init__.py
easy_ml_config/configuration.py
easy_ml_config/py.typed
easy_ml_config-1.2.0.dist-info/METADATA
easy_ml_config-1.2.0.dist-info/WHEEL
easy_ml_config-1.2.0.dist-info/licenses/LICENSE
easy_ml_config-1.2.0.dist-info/RECORD
