Metadata-Version: 2.4
Name: easy-ml-config
Version: 1.2.0
Summary: provides a convenient base configuration class for machine learning projects
Author-email: Nan Lin <nansense97@gmail.com>
License-File: LICENSE
Requires-Python: >=3.11
Requires-Dist: pyyaml>=6.0.2
